pymorphy2/__init__.py
pymorphy2/analyzer.py
pymorphy2/cache.py
pymorphy2/cli.py
pymorphy2/dawg.py
pymorphy2/shapes.py
pymorphy2/tagset.py
pymorphy2/tokenizers.py
pymorphy2/utils.py
pymorphy2/version.py
pymorphy2/lang/__init__.py
pymorphy2/lang/ru/__init__.py
pymorphy2/lang/ru/config.py
pymorphy2/lang/uk/__init__.py
pymorphy2/lang/uk/_prefixes.py
pymorphy2/lang/uk/config.py
pymorphy2/opencorpora_dict/__init__.py
pymorphy2/opencorpora_dict/compile.py
pymorphy2/opencorpora_dict/parse.py
pymorphy2/opencorpora_dict/preprocess.py
pymorphy2/opencorpora_dict/probability.py
pymorphy2/opencorpora_dict/storage.py
pymorphy2/opencorpora_dict/wrapper.py
pymorphy2/units/__init__.py
pymorphy2/units/abbreviations.py
pymorphy2/units/base.py
pymorphy2/units/by_analogy.py
pymorphy2/units/by_hyphen.py
pymorphy2/units/by_lookup.py
pymorphy2/units/by_shape.py
pymorphy2/units/unkn.py
pymorphy2/units/utils.py
pymorphy2-0.9.dist-info/AUTHORS.rst
pymorphy2-0.9.dist-info/METADATA
pymorphy2-0.9.dist-info/WHEEL
pymorphy2-0.9.dist-info/entry_points.txt
pymorphy2-0.9.dist-info/pbr.json
pymorphy2-0.9.dist-info/top_level.txt
pymorphy2-0.9.dist-info/RECORD
