Metadata-Version: 2.1
Name: pymorphy2
Version: 0.9
Summary: Morphological analyzer (POS tagger + inflection engine) for Russian language.
Home-page: https://github.com/kmike/pymorphy2/
Author: Mikhail Korobov
Author-email: kmike84@gmail.com
License: MIT license
Platform: UNKNOWN
Classifier: Development Status :: 4 - Beta
Classifier: Intended Audience :: Developers
Classifier: Intended Audience :: Science/Research
Classifier: License :: OSI Approved :: MIT License
Classifier: Natural Language :: Russian
Classifier: Programming Language :: Python
Classifier: Programming Language :: Python :: 2
Classifier: Programming Language :: Python :: 2.7
Classifier: Programming Language :: Python :: 3
Classifier: Programming Language :: Python :: 3.5
Classifier: Programming Language :: Python :: 3.6
Classifier: Programming Language :: Python :: 3.7
Classifier: Programming Language :: Python :: 3.8
Classifier: Programming Language :: Python :: Implementation :: CPython
Classifier: Programming Language :: Python :: Implementation :: PyPy
Classifier: Topic :: Software Development :: Libraries :: Python Modules
Classifier: Topic :: Scientific/Engineering :: Information Analysis
Classifier: Topic :: Text Processing :: Linguistic
Requires-Dist: dawg-python (>=0.7.1)
Requires-Dist: pymorphy2-dicts-ru (<3.0,>=2.4)
Requires-Dist: docopt (>=0.6)
Provides-Extra: fast
Requires-Dist: DAWG (>=0.8) ; extra == 'fast'
